{
  "status": true,
  "message": "Video Found",
  "video_data": {
    "author": "Cocomelon - Nursery Rhymes",
    "length": 151,
    "thumbnail": "https://i.ytimg.com/vi/ho08YLYDM88/sddefault.jpg",
    "title": "Happy Birthday Song  CoComelon Nursery Rhymes & Kids Songs",
    "views": 994999609,
    "publish_date": {
      "publish_year": 2017,
      "publish_month": 11,
      "publish_day": 15,
      "publish_hour": 0,
      "publish_minute": 0
    },
    "streams": {
      "expiresInSeconds": "21540",
      "formats": [
        {
          "itag": 18,
          "url": "https://rr1---sn-jtcxg-aixr.googlevideo.com/videoplayback?expire=1721918184&ei=iA6iZsbDDrSbhcIP3vGAsAI&ip=72.255.32.221&id=o-AIfkNKKhLT-lA4V_ZUFTQvmtZdu6OuWKlqXK1t_z6xlr&itag=18&source=youtube&requiressl=yes&xpc=EgVo2aDSNQ%3D%3D&mh=Or&mm=31%2C29&mn=sn-jtcxg-aixr%2Csn-hju7enll&ms=au%2Crdu&mv=m&mvi=1&pl=24&initcwndbps=463750&vprv=1&svpuc=1&mime=video%2Fmp4&rqh=1&gir=yes&clen=12332802&ratebypass=yes&dur=150.767&lmt=1634274746428384&mt=1721896397&fvip=5&c=ANDROID_TESTSUITE&txp=5538434&sparams=expire%2Cei%2Cip%2Cid%2Citag%2Csource%2Crequiressl%2Cxpc%2Cvprv%2Csvpuc%2Cmime%2Crqh%2Cgir%2Cclen%2Cratebypass%2Cdur%2Clmt&sig=AJfQdSswRAIgeHs_NomM7_XJAIj35ckn6cOzzZ57OfOtpdfhH24mqMcCIEnjbcOFAQDc4p8dLfrgAa1JoHgapS8TcUiwxHJIdBAA&lsparams=mh%2Cmm%2Cmn%2Cms%2Cmv%2Cmvi%2Cpl%2Cinitcwndbps&lsig=AGtxev0wRQIgKbqKmNZwRGPiI2UyTXhKIU8MGbso7laLX2z8k-XxzxQCIQCKQ2mzp1kpE79FK1iDmfx1J1vuKDLa0OzAkpZKisJhKw%3D%3D",
          "mimeType": "video/mp4; codecs=\"avc1.42001E, mp4a.40.2\"",
          "bitrate": 654659,
          "width": 640,
          "height": 360,
          "lastModified": "1634274746428384",
          "contentLength": "12332802",
          "quality": "medium",
          "fps": 24,
          "qualityLabel": "360p",
          "projectionType": "RECTANGULAR",
          "averageBitrate": 654403,
          "audioQuality": "AUDIO_QUALITY_LOW",
          "approxDurationMs": "150767",
          "audioSampleRate": "44100",
          "audioChannels": 2
        }
      ],
      "adaptiveFormats": [
        {
          "itag": 137,
          "url": "https://rr1---sn-jtcxg-aixr.googlevideo.com/videoplayback?expire=1721918184&ei=iA6iZsbDDrSbhcIP3vGAsAI&ip=72.255.32.221&id=o-AIfkNKKhLT-lA4V_ZUFTQvmtZdu6OuWKlqXK1t_z6xlr&itag=137&source=youtube&requiressl=yes&xpc=EgVo2aDSNQ%3D%3D&mh=Or&mm=31%2C29&mn=sn-jtcxg-aixr%2Csn-hju7enll&ms=au%2Crdu&mv=m&mvi=1&pl=24&initcwndbps=463750&vprv=1&svpuc=1&mime=video%2Fmp4&rqh=1&gir=yes&clen=44814858&dur=150.708&lmt=1634274614355952&mt=1721896397&fvip=5&keepalive=yes&c=ANDROID_TESTSUITE&txp=5535434&sparams=expire%2Cei%2Cip%2Cid%2Citag%2Csource%2Crequiressl%2Cxpc%2Cvprv%2Csvpuc%2Cmime%2Crqh%2Cgir%2Cclen%2Cdur%2Clmt&sig=AJfQdSswRQIgKo9z2KFB-7crHdhO1MagsPCzGJobMaTxJVZEuGwxF20CIQC4lflSPzNt1pFTJhrp1lPY4oIMSxhj30tnoXn0m9FCQQ%3D%3D&lsparams=mh%2Cmm%2Cmn%2Cms%2Cmv%2Cmvi%2Cpl%2Cinitcwndbps&lsig=AGtxev0wRQIgKbqKmNZwRGPiI2UyTXhKIU8MGbso7laLX2z8k-XxzxQCIQCKQ2mzp1kpE79FK1iDmfx1J1vuKDLa0OzAkpZKisJhKw%3D%3D",
          "mimeType": "video/mp4; codecs=\"avc1.640028\"",
          "bitrate": 4342885,
          "width": 1920,
          "height": 1080,
          "initRange": {
            "start": "0",
            "end": "741"
          },
          "indexRange": {
            "start": "742",
            "end": "1121"
          },
          "lastModified": "1634274614355952",
          "contentLength": "44814858",
          "quality": "hd1080",
          "fps": 24,
          "qualityLabel": "1080p",
          "projectionType": "RECTANGULAR",
          "averageBitrate": 2378897,
          "approxDurationMs": "150708"
        },
        {
          "itag": 399,
          "url": "https://rr1---sn-jtcxg-aixr.googlevideo.com/videoplayback?expire=1721918184&ei=iA6iZsbDDrSbhcIP3vGAsAI&ip=72.255.32.221&id=o-AIfkNKKhLT-lA4V_ZUFTQvmtZdu6OuWKlqXK1t_z6xlr&itag=399&source=youtube&requiressl=yes&xpc=EgVo2aDSNQ%3D%3D&mh=Or&mm=31%2C29&mn=sn-jtcxg-aixr%2Csn-hju7enll&ms=au%2Crdu&mv=m&mvi=1&pl=24&initcwndbps=463750&vprv=1&svpuc=1&mime=video%2Fmp4&rqh=1&gir=yes&clen=27732236&dur=150.708&lmt=1634275705585910&mt=1721896397&fvip=5&keepalive=yes&c=ANDROID_TESTSUITE&txp=5532434&sparams=expire%2Cei%2Cip%2Cid%2Citag%2Csource%2Crequiressl%2Cxpc%2Cvprv%2Csvpuc%2Cmime%2Crqh%2Cgir%2Cclen%2Cdur%2Clmt&sig=AJfQdSswRAIgNxJdZ77Hvd1rjmX8ZLvDYIesPhQ_y1KU8ljndN9V2a8CICWQ29wRZH9hDSLWab0kCJkOjI7Q2gtUAtKjhaca1D70&lsparams=mh%2Cmm%2Cmn%2Cms%2Cmv%2Cmvi%2Cpl%2Cinitcwndbps&lsig=AGtxev0wRQIgKbqKmNZwRGPiI2UyTXhKIU8MGbso7laLX2z8k-XxzxQCIQCKQ2mzp1kpE79FK1iDmfx1J1vuKDLa0OzAkpZKisJhKw%3D%3D",
          "mimeType": "video/mp4; codecs=\"av01.0.08M.08\"",
          "bitrate": 2859346,
          "width": 1920,
          "height": 1080,
          "initRange": {
            "start": "0",
            "end": "699"
          },
          "indexRange": {
            "start": "700",
            "end": "1079"
          },
          "lastModified": "1634275705585910",
          "contentLength": "27732236",
          "quality": "hd1080",
          "fps": 24,
          "qualityLabel": "1080p",
          "projectionType": "RECTANGULAR",
          "averageBitrate": 1472104,
          "colorInfo": {
            "primaries": "COLOR_PRIMARIES_BT709",
            "transferCharacteristics": "COLOR_TRANSFER_CHARACTERISTICS_BT709",
            "matrixCoefficients": "COLOR_MATRIX_COEFFICIENTS_BT709"
          },
          "approxDurationMs": "150708"
        },
        {
          "itag": 136,
          "url": "https://rr1---sn-jtcxg-aixr.googlevideo.com/videoplayback?expire=1721918184&ei=iA6iZsbDDrSbhcIP3vGAsAI&ip=72.255.32.221&id=o-AIfkNKKhLT-lA4V_ZUFTQvmtZdu6OuWKlqXK1t_z6xlr&itag=136&source=youtube&requiressl=yes&xpc=EgVo2aDSNQ%3D%3D&mh=Or&mm=31%2C29&mn=sn-jtcxg-aixr%2Csn-hju7enll&ms=au%2Crdu&mv=m&mvi=1&pl=24&initcwndbps=463750&vprv=1&svpuc=1&mime=video%2Fmp4&rqh=1&gir=yes&clen=14618656&dur=150.708&lmt=1634274830781445&mt=1721896397&fvip=5&keepalive=yes&c=ANDROID_TESTSUITE&txp=5535434&sparams=expire%2Cei%2Cip%2Cid%2Citag%2Csource%2Crequiressl%2Cxpc%2Cvprv%2Csvpuc%2Cmime%2Crqh%2Cgir%2Cclen%2Cdur%2Clmt&sig=AJfQdSswRQIgQ7irUB2a_NIqVx3G6UwVKvAyLZQ3VmaBKWaTVL3Kx0oCIQDQNJgNu1qAvHXAlV2UAuJpktxtRgF1DT90GiJneVvlng%3D%3D&lsparams=mh%2Cmm%2Cmn%2Cms%2Cmv%2Cmvi%2Cpl%2Cinitcwndbps&lsig=AGtxev0wRQIgKbqKmNZwRGPiI2UyTXhKIU8MGbso7laLX2z8k-XxzxQCIQCKQ2mzp1kpE79FK1iDmfx1J1vuKDLa0OzAkpZKisJhKw%3D%3D",
          "mimeType": "video/mp4; codecs=\"avc1.4d401f\"",
          "bitrate": 1556577,
          "width": 1280,
          "height": 720,
          "initRange": {
            "start": "0",
            "end": "739"
          },
          "indexRange": {
            "start": "740",
            "end": "1119"
          },
          "lastModified": "1634274830781445",
          "contentLength": "14618656",
          "quality": "hd720",
          "fps": 24,
          "qualityLabel": "720p",
          "projectionType": "RECTANGULAR",
          "averageBitrate": 775998,
          "approxDurationMs": "150708"
        },
        {
          "itag": 247,
          "url": "https://rr1---sn-jtcxg-aixr.googlevideo.com/videoplayback?expire=1721918184&ei=iA6iZsbDDrSbhcIP3vGAsAI&ip=72.255.32.221&id=o-AIfkNKKhLT-lA4V_ZUFTQvmtZdu6OuWKlqXK1t_z6xlr&itag=247&source=youtube&requiressl=yes&xpc=EgVo2aDSNQ%3D%3D&mh=Or&mm=31%2C29&mn=sn-jtcxg-aixr%2Csn-hju7enll&ms=au%2Crdu&mv=m&mvi=1&pl=24&initcwndbps=463750&vprv=1&svpuc=1&mime=video%2Fwebm&rqh=1&gir=yes&clen=15170238&dur=150.708&lmt=1634274873402416&mt=1721896397&fvip=5&keepalive=yes&c=ANDROID_TESTSUITE&txp=5535434&sparams=expire%2Cei%2Cip%2Cid%2Citag%2Csource%2Crequiressl%2Cxpc%2Cvprv%2Csvpuc%2Cmime%2Crqh%2Cgir%2Cclen%2Cdur%2Clmt&sig=AJfQdSswRgIhAKZVOqYBghL496UGdnt2R97aF8Bzhu1PjPgbftDMEx3MAiEA7XIHfBoCzk6xq9-CDN8dZOQ4P2nB9mX9MOnZW36Mh9w%3D&lsparams=mh%2Cmm%2Cmn%2Cms%2Cmv%2Cmvi%2Cpl%2Cinitcwndbps&lsig=AGtxev0wRQIgKbqKmNZwRGPiI2UyTXhKIU8MGbso7laLX2z8k-XxzxQCIQCKQ2mzp1kpE79FK1iDmfx1J1vuKDLa0OzAkpZKisJhKw%3D%3D",
          "mimeType": "video/webm; codecs=\"vp9\"",
          "bitrate": 1491760,
          "width": 1280,
          "height": 720,
          "initRange": {
            "start": "0",
            "end": "219"
          },
          "indexRange": {
            "start": "220",
            "end": "703"
          },
          "lastModified": "1634274873402416",
          "contentLength": "15170238",
          "quality": "hd720",
          "fps": 24,
          "qualityLabel": "720p",
          "projectionType": "RECTANGULAR",
          "averageBitrate": 805278,
          "colorInfo": {
            "primaries": "COLOR_PRIMARIES_BT709",
            "transferCharacteristics": "COLOR_TRANSFER_CHARACTERISTICS_BT709",
            "matrixCoefficients": "COLOR_MATRIX_COEFFICIENTS_BT709"
          },
          "approxDurationMs": "150708"
        },
        {
          "itag": 398,
          "url": "https://rr1---sn-jtcxg-aixr.googlevideo.com/videoplayback?expire=1721918184&ei=iA6iZsbDDrSbhcIP3vGAsAI&ip=72.255.32.221&id=o-AIfkNKKhLT-lA4V_ZUFTQvmtZdu6OuWKlqXK1t_z6xlr&itag=398&source=youtube&requiressl=yes&xpc=EgVo2aDSNQ%3D%3D&mh=Or&mm=31%2C29&mn=sn-jtcxg-aixr%2Csn-hju7enll&ms=au%2Crdu&mv=m&mvi=1&pl=24&initcwndbps=463750&vprv=1&svpuc=1&mime=video%2Fmp4&rqh=1&gir=yes&clen=16740972&dur=150.708&lmt=1634274631192363&mt=1721896397&fvip=5&keepalive=yes&c=ANDROID_TESTSUITE&txp=5532434&sparams=expire%2Cei%2Cip%2Cid%2Citag%2Csource%2Crequiressl%2Cxpc%2Cvprv%2Csvpuc%2Cmime%2Crqh%2Cgir%2Cclen%2Cdur%2Clmt&sig=AJfQdSswRQIgBFdLlp8aBLujsJozsqwNgT8h_-tVTm7ngOLj4eCaaAgCIQCCr7j0UgMiANYxKDCzNuoScDLs6rFpTMTDGgH1UDfJVg%3D%3D&lsparams=mh%2Cmm%2Cmn%2Cms%2Cmv%2Cmvi%2Cpl%2Cinitcwndbps&lsig=AGtxev0wRQIgKbqKmNZwRGPiI2UyTXhKIU8MGbso7laLX2z8k-XxzxQCIQCKQ2mzp1kpE79FK1iDmfx1J1vuKDLa0OzAkpZKisJhKw%3D%3D",
          "mimeType": "video/mp4; codecs=\"av01.0.05M.08\"",
          "bitrate": 1600653,
          "width": 1280,
          "height": 720,
          "initRange": {
            "start": "0",
            "end": "699"
          },
          "indexRange": {
            "start": "700",
            "end": "1079"
          },
          "lastModified": "1634274631192363",
          "contentLength": "16740972",
          "quality": "hd720",
          "fps": 24,
          "qualityLabel": "720p",
          "projectionType": "RECTANGULAR",
          "averageBitrate": 888657,
          "colorInfo": {
            "primaries": "COLOR_PRIMARIES_BT709",
            "transferCharacteristics": "COLOR_TRANSFER_CHARACTERISTICS_BT709",
            "matrixCoefficients": "COLOR_MATRIX_COEFFICIENTS_BT709"
          },
          "approxDurationMs": "150708"
        },
        {
          "itag": 135,
          "url": "https://rr1---sn-jtcxg-aixr.googlevideo.com/videoplayback?expire=1721918184&ei=iA6iZsbDDrSbhcIP3vGAsAI&ip=72.255.32.221&id=o-AIfkNKKhLT-lA4V_ZUFTQvmtZdu6OuWKlqXK1t_z6xlr&itag=135&source=youtube&requiressl=yes&xpc=EgVo2aDSNQ%3D%3D&mh=Or&mm=31%2C29&mn=sn-jtcxg-aixr%2Csn-hju7enll&ms=au%2Crdu&mv=m&mvi=1&pl=24&initcwndbps=463750&vprv=1&svpuc=1&mime=video%2Fmp4&rqh=1&gir=yes&clen=8266470&dur=150.708&lmt=1634274824038909&mt=1721896397&fvip=5&keepalive=yes&c=ANDROID_TESTSUITE&txp=5535434&sparams=expire%2Cei%2Cip%2Cid%2Citag%2Csource%2Crequiressl%2Cxpc%2Cvprv%2Csvpuc%2Cmime%2Crqh%2Cgir%2Cclen%2Cdur%2Clmt&sig=AJfQdSswRQIgM2QdskWunGr4Ui584J4xayf9_HRo7MIuw0kP4IGcVosCIQCBMzyXIVNLeOe9SWU-bQQckPXSkYitElqyojXNnzmabQ%3D%3D&lsparams=mh%2Cmm%2Cmn%2Cms%2Cmv%2Cmvi%2Cpl%2Cinitcwndbps&lsig=AGtxev0wRQIgKbqKmNZwRGPiI2UyTXhKIU8MGbso7laLX2z8k-XxzxQCIQCKQ2mzp1kpE79FK1iDmfx1J1vuKDLa0OzAkpZKisJhKw%3D%3D",
          "mimeType": "video/mp4; codecs=\"avc1.4d401e\"",
          "bitrate": 879017,
          "width": 854,
          "height": 480,
          "initRange": {
            "start": "0",
            "end": "740"
          },
          "indexRange": {
            "start": "741",
            "end": "1120"
          },
          "lastModified": "1634274824038909",
          "contentLength": "8266470",
          "quality": "large",
          "fps": 24,
          "qualityLabel": "480p",
          "projectionType": "RECTANGULAR",
          "averageBitrate": 438807,
          "approxDurationMs": "150708"
        },
        {
          "itag": 244,
          "url": "https://rr1---sn-jtcxg-aixr.googlevideo.com/videoplayback?expire=1721918184&ei=iA6iZsbDDrSbhcIP3vGAsAI&ip=72.255.32.221&id=o-AIfkNKKhLT-lA4V_ZUFTQvmtZdu6OuWKlqXK1t_z6xlr&itag=244&source=youtube&requiressl=yes&xpc=EgVo2aDSNQ%3D%3D&mh=Or&mm=31%2C29&mn=sn-jtcxg-aixr%2Csn-hju7enll&ms=au%2Crdu&mv=m&mvi=1&pl=24&initcwndbps=463750&vprv=1&svpuc=1&mime=video%2Fwebm&rqh=1&gir=yes&clen=9248867&dur=150.708&lmt=1634274881498491&mt=1721896397&fvip=5&keepalive=yes&c=ANDROID_TESTSUITE&txp=5535434&sparams=expire%2Cei%2Cip%2Cid%2Citag%2Csource%2Crequiressl%2Cxpc%2Cvprv%2Csvpuc%2Cmime%2Crqh%2Cgir%2Cclen%2Cdur%2Clmt&sig=AJfQdSswRAIgPpV5FcRVUt7f4-vd7jh1wW4aql6sq-An4lTvdvf9wToCIC8_EClJObJJ3og0JE4JEGEF48FbaRk8xKoBoJeLiSPf&lsparams=mh%2Cmm%2Cmn%2Cms%2Cmv%2Cmvi%2Cpl%2Cinitcwndbps&lsig=AGtxev0wRQIgKbqKmNZwRGPiI2UyTXhKIU8MGbso7laLX2z8k-XxzxQCIQCKQ2mzp1kpE79FK1iDmfx1J1vuKDLa0OzAkpZKisJhKw%3D%3D",
          "mimeType": "video/webm; codecs=\"vp9\"",
          "bitrate": 748562,
          "width": 854,
          "height": 480,
          "initRange": {
            "start": "0",
            "end": "219"
          },
          "indexRange": {
            "start": "220",
            "end": "703"
          },
          "lastModified": "1634274881498491",
          "contentLength": "9248867",
          "quality": "large",
          "fps": 24,
          "qualityLabel": "480p",
          "projectionType": "RECTANGULAR",
          "averageBitrate": 490955,
          "colorInfo": {
            "primaries": "COLOR_PRIMARIES_BT709",
            "transferCharacteristics": "COLOR_TRANSFER_CHARACTERISTICS_BT709",
            "matrixCoefficients": "COLOR_MATRIX_COEFFICIENTS_BT709"
          },
          "approxDurationMs": "150708"
        },
        {
          "itag": 397,
          "url": "https://rr1---sn-jtcxg-aixr.googlevideo.com/videoplayback?expire=1721918184&ei=iA6iZsbDDrSbhcIP3vGAsAI&ip=72.255.32.221&id=o-AIfkNKKhLT-lA4V_ZUFTQvmtZdu6OuWKlqXK1t_z6xlr&itag=397&source=youtube&requiressl=yes&xpc=EgVo2aDSNQ%3D%3D&mh=Or&mm=31%2C29&mn=sn-jtcxg-aixr%2Csn-hju7enll&ms=au%2Crdu&mv=m&mvi=1&pl=24&initcwndbps=463750&vprv=1&svpuc=1&mime=video%2Fmp4&rqh=1&gir=yes&clen=8899854&dur=150.708&lmt=1634274538123717&mt=1721896397&fvip=5&keepalive=yes&c=ANDROID_TESTSUITE&txp=5532434&sparams=expire%2Cei%2Cip%2Cid%2Citag%2Csource%2Crequiressl%2Cxpc%2Cvprv%2Csvpuc%2Cmime%2Crqh%2Cgir%2Cclen%2Cdur%2Clmt&sig=AJfQdSswRQIgfddYDhxk4IcYHUjES1Ll-eeZ3Q8vtxlsYCuj0SlbEDsCIQCvzZvGrsVnqeVVFvlK5KvwSMd_dpqFyvFOuMGApjr2fw%3D%3D&lsparams=mh%2Cmm%2Cmn%2Cms%2Cmv%2Cmvi%2Cpl%2Cinitcwndbps&lsig=AGtxev0wRQIgKbqKmNZwRGPiI2UyTXhKIU8MGbso7laLX2z8k-XxzxQCIQCKQ2mzp1kpE79FK1iDmfx1J1vuKDLa0OzAkpZKisJhKw%3D%3D",
          "mimeType": "video/mp4; codecs=\"av01.0.04M.08\"",
          "bitrate": 769146,
          "width": 854,
          "height": 480,
          "initRange": {
            "start": "0",
            "end": "699"
          },
          "indexRange": {
            "start": "700",
            "end": "1079"
          },
          "lastModified": "1634274538123717",
          "contentLength": "8899854",
          "quality": "large",
          "fps": 24,
          "qualityLabel": "480p",
          "projectionType": "RECTANGULAR",
          "averageBitrate": 472429,
          "colorInfo": {
            "primaries": "COLOR_PRIMARIES_BT709",
            "transferCharacteristics": "COLOR_TRANSFER_CHARACTERISTICS_BT709",
            "matrixCoefficients": "COLOR_MATRIX_COEFFICIENTS_BT709"
          },
          "approxDurationMs": "150708"
        },
        {
          "itag": 134,
          "url": "https://rr1---sn-jtcxg-aixr.googlevideo.com/videoplayback?expire=1721918184&ei=iA6iZsbDDrSbhcIP3vGAsAI&ip=72.255.32.221&id=o-AIfkNKKhLT-lA4V_ZUFTQvmtZdu6OuWKlqXK1t_z6xlr&itag=134&source=youtube&requiressl=yes&xpc=EgVo2aDSNQ%3D%3D&mh=Or&mm=31%2C29&mn=sn-jtcxg-aixr%2Csn-hju7enll&ms=au%2Crdu&mv=m&mvi=1&pl=24&initcwndbps=463750&vprv=1&svpuc=1&mime=video%2Fmp4&rqh=1&gir=yes&clen=5562860&dur=150.708&lmt=1634274831637230&mt=1721896397&fvip=5&keepalive=yes&c=ANDROID_TESTSUITE&txp=5535434&sparams=expire%2Cei%2Cip%2Cid%2Citag%2Csource%2Crequiressl%2Cxpc%2Cvprv%2Csvpuc%2Cmime%2Crqh%2Cgir%2Cclen%2Cdur%2Clmt&sig=AJfQdSswRQIgecSP1ntHpoTb5HoItHLlFd2Bh6xyvYOirO_lO-Sa7ZcCIQCZDU4_2NiR6D1fqlSNjDCy-524_3XdoUw1a0b3GsOlfA%3D%3D&lsparams=mh%2Cmm%2Cmn%2Cms%2Cmv%2Cmvi%2Cpl%2Cinitcwndbps&lsig=AGtxev0wRQIgKbqKmNZwRGPiI2UyTXhKIU8MGbso7laLX2z8k-XxzxQCIQCKQ2mzp1kpE79FK1iDmfx1J1vuKDLa0OzAkpZKisJhKw%3D%3D",
          "mimeType": "video/mp4; codecs=\"avc1.4d401e\"",
          "bitrate": 577108,
          "width": 640,
          "height": 360,
          "initRange": {
            "start": "0",
            "end": "740"
          },
          "indexRange": {
            "start": "741",
            "end": "1120"
          },
          "lastModified": "1634274831637230",
          "contentLength": "5562860",
          "quality": "medium",
          "fps": 24,
          "qualityLabel": "360p",
          "projectionType": "RECTANGULAR",
          "averageBitrate": 295292,
          "highReplication": true,
          "approxDurationMs": "150708"
        },
        {
          "itag": 243,
          "url": "https://rr1---sn-jtcxg-aixr.googlevideo.com/videoplayback?expire=1721918184&ei=iA6iZsbDDrSbhcIP3vGAsAI&ip=72.255.32.221&id=o-AIfkNKKhLT-lA4V_ZUFTQvmtZdu6OuWKlqXK1t_z6xlr&itag=243&source=youtube&requiressl=yes&xpc=EgVo2aDSNQ%3D%3D&mh=Or&mm=31%2C29&mn=sn-jtcxg-aixr%2Csn-hju7enll&ms=au%2Crdu&mv=m&mvi=1&pl=24&initcwndbps=463750&vprv=1&svpuc=1&mime=video%2Fwebm&rqh=1&gir=yes&clen=6036569&dur=150.708&lmt=1634274871338056&mt=1721896397&fvip=5&keepalive=yes&c=ANDROID_TESTSUITE&txp=5535434&sparams=expire%2Cei%2Cip%2Cid%2Citag%2Csource%2Crequiressl%2Cxpc%2Cvprv%2Csvpuc%2Cmime%2Crqh%2Cgir%2Cclen%2Cdur%2Clmt&sig=AJfQdSswRgIhAIe8t0FkXdaC98da3r_ODNaMnRpfyYGe_xdI8xYdLro-AiEArOnSrHPz6fjmXCg-nHk-yR-xTRdu_qqbxbKAaV-4VSo%3D&lsparams=mh%2Cmm%2Cmn%2Cms%2Cmv%2Cmvi%2Cpl%2Cinitcwndbps&lsig=AGtxev0wRQIgKbqKmNZwRGPiI2UyTXhKIU8MGbso7laLX2z8k-XxzxQCIQCKQ2mzp1kpE79FK1iDmfx1J1vuKDLa0OzAkpZKisJhKw%3D%3D",
          "mimeType": "video/webm; codecs=\"vp9\"",
          "bitrate": 410183,
          "width": 640,
          "height": 360,
          "initRange": {
            "start": "0",
            "end": "219"
          },
          "indexRange": {
            "start": "220",
            "end": "703"
          },
          "lastModified": "1634274871338056",
          "contentLength": "6036569",
          "quality": "medium",
          "fps": 24,
          "qualityLabel": "360p",
          "projectionType": "RECTANGULAR",
          "averageBitrate": 320437,
          "colorInfo": {
            "primaries": "COLOR_PRIMARIES_BT709",
            "transferCharacteristics": "COLOR_TRANSFER_CHARACTERISTICS_BT709",
            "matrixCoefficients": "COLOR_MATRIX_COEFFICIENTS_BT709"
          },
          "approxDurationMs": "150708"
        },
        {
          "itag": 396,
          "url": "https://rr1---sn-jtcxg-aixr.googlevideo.com/videoplayback?expire=1721918184&ei=iA6iZsbDDrSbhcIP3vGAsAI&ip=72.255.32.221&id=o-AIfkNKKhLT-lA4V_ZUFTQvmtZdu6OuWKlqXK1t_z6xlr&itag=396&source=youtube&requiressl=yes&xpc=EgVo2aDSNQ%3D%3D&mh=Or&mm=31%2C29&mn=sn-jtcxg-aixr%2Csn-hju7enll&ms=au%2Crdu&mv=m&mvi=1&pl=24&initcwndbps=463750&vprv=1&svpuc=1&mime=video%2Fmp4&rqh=1&gir=yes&clen=5285025&dur=150.708&lmt=1634274590852038&mt=1721896397&fvip=5&keepalive=yes&c=ANDROID_TESTSUITE&txp=5532434&sparams=expire%2Cei%2Cip%2Cid%2Citag%2Csource%2Crequiressl%2Cxpc%2Cvprv%2Csvpuc%2Cmime%2Crqh%2Cgir%2Cclen%2Cdur%2Clmt&sig=AJfQdSswRQIhAKRvtIH-t96qpmOwBSIqUbgSIBM14ZXDSDcboJ4LtL_0AiAYSIn7R5Y0dxjapPUZ9qlC9UK7B6kTA6oyI04WZLSYqw%3D%3D&lsparams=mh%2Cmm%2Cmn%2Cms%2Cmv%2Cmvi%2Cpl%2Cinitcwndbps&lsig=AGtxev0wRQIgKbqKmNZwRGPiI2UyTXhKIU8MGbso7laLX2z8k-XxzxQCIQCKQ2mzp1kpE79FK1iDmfx1J1vuKDLa0OzAkpZKisJhKw%3D%3D",
          "mimeType": "video/mp4; codecs=\"av01.0.01M.08\"",
          "bitrate": 400830,
          "width": 640,
          "height": 360,
          "initRange": {
            "start": "0",
            "end": "699"
          },
          "indexRange": {
            "start": "700",
            "end": "1079"
          },
          "lastModified": "1634274590852038",
          "contentLength": "5285025",
          "quality": "medium",
          "fps": 24,
          "qualityLabel": "360p",
          "projectionType": "RECTANGULAR",
          "averageBitrate": 280543,
          "colorInfo": {
            "primaries": "COLOR_PRIMARIES_BT709",
            "transferCharacteristics": "COLOR_TRANSFER_CHARACTERISTICS_BT709",
            "matrixCoefficients": "COLOR_MATRIX_COEFFICIENTS_BT709"
          },
          "approxDurationMs": "150708"
        },
        {
          "itag": 133,
          "url": "https://rr1---sn-jtcxg-aixr.googlevideo.com/videoplayback?expire=1721918184&ei=iA6iZsbDDrSbhcIP3vGAsAI&ip=72.255.32.221&id=o-AIfkNKKhLT-lA4V_ZUFTQvmtZdu6OuWKlqXK1t_z6xlr&itag=133&source=youtube&requiressl=yes&xpc=EgVo2aDSNQ%3D%3D&mh=Or&mm=31%2C29&mn=sn-jtcxg-aixr%2Csn-hju7enll&ms=au%2Crdu&mv=m&mvi=1&pl=24&initcwndbps=463750&vprv=1&svpuc=1&mime=video%2Fmp4&rqh=1&gir=yes&clen=3067508&dur=150.708&lmt=1634274829727325&mt=1721896397&fvip=5&keepalive=yes&c=ANDROID_TESTSUITE&txp=5535434&sparams=expire%2Cei%2Cip%2Cid%2Citag%2Csource%2Crequiressl%2Cxpc%2Cvprv%2Csvpuc%2Cmime%2Crqh%2Cgir%2Cclen%2Cdur%2Clmt&sig=AJfQdSswRgIhAIoFlaw2mDNYxy6yQM0e9WSOr8vxqLtPcAB3qRbmkpJbAiEA0akX-atMPgmJD3eAIXci_4iWEIhRQzq2g17MXOHEk8o%3D&lsparams=mh%2Cmm%2Cmn%2Cms%2Cmv%2Cmvi%2Cpl%2Cinitcwndbps&lsig=AGtxev0wRQIgKbqKmNZwRGPiI2UyTXhKIU8MGbso7laLX2z8k-XxzxQCIQCKQ2mzp1kpE79FK1iDmfx1J1vuKDLa0OzAkpZKisJhKw%3D%3D",
          "mimeType": "video/mp4; codecs=\"avc1.4d4015\"",
          "bitrate": 228432,
          "width": 426,
          "height": 240,
          "initRange": {
            "start": "0",
            "end": "739"
          },
          "indexRange": {
            "start": "740",
            "end": "1119"
          },
          "lastModified": "1634274829727325",
          "contentLength": "3067508",
          "quality": "small",
          "fps": 24,
          "qualityLabel": "240p",
          "projectionType": "RECTANGULAR",
          "averageBitrate": 162831,
          "approxDurationMs": "150708"
        },
        {
          "itag": 242,
          "url": "https://rr1---sn-jtcxg-aixr.googlevideo.com/videoplayback?expire=1721918184&ei=iA6iZsbDDrSbhcIP3vGAsAI&ip=72.255.32.221&id=o-AIfkNKKhLT-lA4V_ZUFTQvmtZdu6OuWKlqXK1t_z6xlr&itag=242&source=youtube&requiressl=yes&xpc=EgVo2aDSNQ%3D%3D&mh=Or&mm=31%2C29&mn=sn-jtcxg-aixr%2Csn-hju7enll&ms=au%2Crdu&mv=m&mvi=1&pl=24&initcwndbps=463750&vprv=1&svpuc=1&mime=video%2Fwebm&rqh=1&gir=yes&clen=3486135&dur=150.708&lmt=1634274867789598&mt=1721896397&fvip=5&keepalive=yes&c=ANDROID_TESTSUITE&txp=5535434&sparams=expire%2Cei%2Cip%2Cid%2Citag%2Csource%2Crequiressl%2Cxpc%2Cvprv%2Csvpuc%2Cmime%2Crqh%2Cgir%2Cclen%2Cdur%2Clmt&sig=AJfQdSswRQIgPA6VJflHA8qIaYTedhcVkazG7BngXL5_DYTKmKVBVJcCIQD54jWhXt4znSrJDnFSsij5PaK8CTIwKiYOri8KpD5rwA%3D%3D&lsparams=mh%2Cmm%2Cmn%2Cms%2Cmv%2Cmvi%2Cpl%2Cinitcwndbps&lsig=AGtxev0wRQIgKbqKmNZwRGPiI2UyTXhKIU8MGbso7laLX2z8k-XxzxQCIQCKQ2mzp1kpE79FK1iDmfx1J1vuKDLa0OzAkpZKisJhKw%3D%3D",
          "mimeType": "video/webm; codecs=\"vp9\"",
          "bitrate": 223564,
          "width": 426,
          "height": 240,
          "initRange": {
            "start": "0",
            "end": "218"
          },
          "indexRange": {
            "start": "219",
            "end": "702"
          },
          "lastModified": "1634274867789598",
          "contentLength": "3486135",
          "quality": "small",
          "fps": 24,
          "qualityLabel": "240p",
          "projectionType": "RECTANGULAR",
          "averageBitrate": 185053,
          "colorInfo": {
            "primaries": "COLOR_PRIMARIES_BT709",
            "transferCharacteristics": "COLOR_TRANSFER_CHARACTERISTICS_BT709",
            "matrixCoefficients": "COLOR_MATRIX_COEFFICIENTS_BT709"
          },
          "approxDurationMs": "150708"
        },
        {
          "itag": 395,
          "url": "https://rr1---sn-jtcxg-aixr.googlevideo.com/videoplayback?expire=1721918184&ei=iA6iZsbDDrSbhcIP3vGAsAI&ip=72.255.32.221&id=o-AIfkNKKhLT-lA4V_ZUFTQvmtZdu6OuWKlqXK1t_z6xlr&itag=395&source=youtube&requiressl=yes&xpc=EgVo2aDSNQ%3D%3D&mh=Or&mm=31%2C29&mn=sn-jtcxg-aixr%2Csn-hju7enll&ms=au%2Crdu&mv=m&mvi=1&pl=24&initcwndbps=463750&vprv=1&svpuc=1&mime=video%2Fmp4&rqh=1&gir=yes&clen=2787205&dur=150.708&lmt=1634274385427284&mt=1721896397&fvip=5&keepalive=yes&c=ANDROID_TESTSUITE&txp=5532434&sparams=expire%2Cei%2Cip%2Cid%2Citag%2Csource%2Crequiressl%2Cxpc%2Cvprv%2Csvpuc%2Cmime%2Crqh%2Cgir%2Cclen%2Cdur%2Clmt&sig=AJfQdSswRQIgI01dmreq0DYL2M-RpAXZLH73OgWrX3zPVmwtIoM_UNoCIQDyIxinpmo4HmiDgmh4wOkdzBNZHn2f6kbH_8CFPif-AA%3D%3D&lsparams=mh%2Cmm%2Cmn%2Cms%2Cmv%2Cmvi%2Cpl%2Cinitcwndbps&lsig=AGtxev0wRQIgKbqKmNZwRGPiI2UyTXhKIU8MGbso7laLX2z8k-XxzxQCIQCKQ2mzp1kpE79FK1iDmfx1J1vuKDLa0OzAkpZKisJhKw%3D%3D",
          "mimeType": "video/mp4; codecs=\"av01.0.00M.08\"",
          "bitrate": 192327,
          "width": 426,
          "height": 240,
          "initRange": {
            "start": "0",
            "end": "699"
          },
          "indexRange": {
            "start": "700",
            "end": "1079"
          },
          "lastModified": "1634274385427284",
          "contentLength": "2787205",
          "quality": "small",
          "fps": 24,
          "qualityLabel": "240p",
          "projectionType": "RECTANGULAR",
          "averageBitrate": 147952,
          "colorInfo": {
            "primaries": "COLOR_PRIMARIES_BT709",
            "transferCharacteristics": "COLOR_TRANSFER_CHARACTERISTICS_BT709",
            "matrixCoefficients": "COLOR_MATRIX_COEFFICIENTS_BT709"
          },
          "approxDurationMs": "150708"
        },
        {
          "itag": 160,
          "url": "https://rr1---sn-jtcxg-aixr.googlevideo.com/videoplayback?expire=1721918184&ei=iA6iZsbDDrSbhcIP3vGAsAI&ip=72.255.32.221&id=o-AIfkNKKhLT-lA4V_ZUFTQvmtZdu6OuWKlqXK1t_z6xlr&itag=160&source=youtube&requiressl=yes&xpc=EgVo2aDSNQ%3D%3D&mh=Or&mm=31%2C29&mn=sn-jtcxg-aixr%2Csn-hju7enll&ms=au%2Crdu&mv=m&mvi=1&pl=24&initcwndbps=463750&vprv=1&svpuc=1&mime=video%2Fmp4&rqh=1&gir=yes&clen=1658709&dur=150.708&lmt=1634274825181880&mt=1721896397&fvip=5&keepalive=yes&c=ANDROID_TESTSUITE&txp=5535434&sparams=expire%2Cei%2Cip%2Cid%2Citag%2Csource%2Crequiressl%2Cxpc%2Cvprv%2Csvpuc%2Cmime%2Crqh%2Cgir%2Cclen%2Cdur%2Clmt&sig=AJfQdSswRQIgCw256g04kn_BdKfsWyHv1kB8WUOllu9wXzBilryx_AMCIQChaz9gvs1Jx31v1-hIi8eNc7bjLj8wa8Jh38lknb14gg%3D%3D&lsparams=mh%2Cmm%2Cmn%2Cms%2Cmv%2Cmvi%2Cpl%2Cinitcwndbps&lsig=AGtxev0wRQIgKbqKmNZwRGPiI2UyTXhKIU8MGbso7laLX2z8k-XxzxQCIQCKQ2mzp1kpE79FK1iDmfx1J1vuKDLa0OzAkpZKisJhKw%3D%3D",
          "mimeType": "video/mp4; codecs=\"avc1.4d400c\"",
          "bitrate": 107573,
          "width": 256,
          "height": 144,
          "initRange": {
            "start": "0",
            "end": "738"
          },
          "indexRange": {
            "start": "739",
            "end": "1118"
          },
          "lastModified": "1634274825181880",
          "contentLength": "1658709",
          "quality": "tiny",
          "fps": 24,
          "qualityLabel": "144p",
          "projectionType": "RECTANGULAR",
          "averageBitrate": 88048,
          "approxDurationMs": "150708"
        },
        {
          "itag": 278,
          "url": "https://rr1---sn-jtcxg-aixr.googlevideo.com/videoplayback?expire=1721918184&ei=iA6iZsbDDrSbhcIP3vGAsAI&ip=72.255.32.221&id=o-AIfkNKKhLT-lA4V_ZUFTQvmtZdu6OuWKlqXK1t_z6xlr&itag=278&source=youtube&requiressl=yes&xpc=EgVo2aDSNQ%3D%3D&mh=Or&mm=31%2C29&mn=sn-jtcxg-aixr%2Csn-hju7enll&ms=au%2Crdu&mv=m&mvi=1&pl=24&initcwndbps=463750&vprv=1&svpuc=1&mime=video%2Fwebm&rqh=1&gir=yes&clen=1638334&dur=150.708&lmt=1634274875069349&mt=1721896397&fvip=5&keepalive=yes&c=ANDROID_TESTSUITE&txp=5535434&sparams=expire%2Cei%2Cip%2Cid%2Citag%2Csource%2Crequiressl%2Cxpc%2Cvprv%2Csvpuc%2Cmime%2Crqh%2Cgir%2Cclen%2Cdur%2Clmt&sig=AJfQdSswRgIhAPvvEh8qlju1ywPlBOGYuNnRzgaMcNv-VLtEAMUJMOsPAiEAmVrM-3vLE1N5t_luvFnK040USulds98GBojsbBfL97M%3D&lsparams=mh%2Cmm%2Cmn%2Cms%2Cmv%2Cmvi%2Cpl%2Cinitcwndbps&lsig=AGtxev0wRQIgKbqKmNZwRGPiI2UyTXhKIU8MGbso7laLX2z8k-XxzxQCIQCKQ2mzp1kpE79FK1iDmfx1J1vuKDLa0OzAkpZKisJhKw%3D%3D",
          "mimeType": "video/webm; codecs=\"vp9\"",
          "bitrate": 96881,
          "width": 256,
          "height": 144,
          "initRange": {
            "start": "0",
            "end": "217"
          },
          "indexRange": {
            "start": "218",
            "end": "700"
          },
          "lastModified": "1634274875069349",
          "contentLength": "1638334",
          "quality": "tiny",
          "fps": 24,
          "qualityLabel": "144p",
          "projectionType": "RECTANGULAR",
          "averageBitrate": 86967,
          "colorInfo": {
            "primaries": "COLOR_PRIMARIES_BT709",
            "transferCharacteristics": "COLOR_TRANSFER_CHARACTERISTICS_BT709",
            "matrixCoefficients": "COLOR_MATRIX_COEFFICIENTS_BT709"
          },
          "approxDurationMs": "150708"
        },
        {
          "itag": 394,
          "url": "https://rr1---sn-jtcxg-aixr.googlevideo.com/videoplayback?expire=1721918184&ei=iA6iZsbDDrSbhcIP3vGAsAI&ip=72.255.32.221&id=o-AIfkNKKhLT-lA4V_ZUFTQvmtZdu6OuWKlqXK1t_z6xlr&itag=394&source=youtube&requiressl=yes&xpc=EgVo2aDSNQ%3D%3D&mh=Or&mm=31%2C29&mn=sn-jtcxg-aixr%2Csn-hju7enll&ms=au%2Crdu&mv=m&mvi=1&pl=24&initcwndbps=463750&vprv=1&svpuc=1&mime=video%2Fmp4&rqh=1&gir=yes&clen=1341299&dur=150.708&lmt=1634274407857077&mt=1721896397&fvip=5&keepalive=yes&c=ANDROID_TESTSUITE&txp=5532434&sparams=expire%2Cei%2Cip%2Cid%2Citag%2Csource%2Crequiressl%2Cxpc%2Cvprv%2Csvpuc%2Cmime%2Crqh%2Cgir%2Cclen%2Cdur%2Clmt&sig=AJfQdSswRQIhAPb9C44_KPG1oRqSVSUMBfud4pMSZtzRa4yeQWR93ISIAiADRNxLI-ME7VlWfTG7r1BIl9YfzRMfVCuROaaQfZf0MQ%3D%3D&lsparams=mh%2Cmm%2Cmn%2Cms%2Cmv%2Cmvi%2Cpl%2Cinitcwndbps&lsig=AGtxev0wRQIgKbqKmNZwRGPiI2UyTXhKIU8MGbso7laLX2z8k-XxzxQCIQCKQ2mzp1kpE79FK1iDmfx1J1vuKDLa0OzAkpZKisJhKw%3D%3D",
          "mimeType": "video/mp4; codecs=\"av01.0.00M.08\"",
          "bitrate": 85317,
          "width": 256,
          "height": 144,
          "initRange": {
            "start": "0",
            "end": "699"
          },
          "indexRange": {
            "start": "700",
            "end": "1079"
          },
          "lastModified": "1634274407857077",
          "contentLength": "1341299",
          "quality": "tiny",
          "fps": 24,
          "qualityLabel": "144p",
          "projectionType": "RECTANGULAR",
          "averageBitrate": 71199,
          "colorInfo": {
            "primaries": "COLOR_PRIMARIES_BT709",
            "transferCharacteristics": "COLOR_TRANSFER_CHARACTERISTICS_BT709",
            "matrixCoefficients": "COLOR_MATRIX_COEFFICIENTS_BT709"
          },
          "approxDurationMs": "150708"
        },
        {
          "itag": 139,
          "url": "https://rr1---sn-jtcxg-aixr.googlevideo.com/videoplayback?expire=1721918184&ei=iA6iZsbDDrSbhcIP3vGAsAI&ip=72.255.32.221&id=o-AIfkNKKhLT-lA4V_ZUFTQvmtZdu6OuWKlqXK1t_z6xlr&itag=139&source=youtube&requiressl=yes&xpc=EgVo2aDSNQ%3D%3D&mh=Or&mm=31%2C29&mn=sn-jtcxg-aixr%2Csn-hju7enll&ms=au%2Crdu&mv=m&mvi=1&pl=24&initcwndbps=463750&vprv=1&svpuc=1&mime=audio%2Fmp4&rqh=1&gir=yes&clen=920541&dur=150.836&lmt=1634201977640971&mt=1721896397&fvip=5&keepalive=yes&c=ANDROID_TESTSUITE&txp=5532434&sparams=expire%2Cei%2Cip%2Cid%2Citag%2Csource%2Crequiressl%2Cxpc%2Cvprv%2Csvpuc%2Cmime%2Crqh%2Cgir%2Cclen%2Cdur%2Clmt&sig=AJfQdSswRQIhANX0F1yj-hmhC81KOPHMtW357H5VVIp5O_1uvfzqnHXRAiBKnPjC9-57OifKh5S0wNqjWzu_WMHFDyillrFXI_vk7w%3D%3D&lsparams=mh%2Cmm%2Cmn%2Cms%2Cmv%2Cmvi%2Cpl%2Cinitcwndbps&lsig=AGtxev0wRQIgKbqKmNZwRGPiI2UyTXhKIU8MGbso7laLX2z8k-XxzxQCIQCKQ2mzp1kpE79FK1iDmfx1J1vuKDLa0OzAkpZKisJhKw%3D%3D",
          "mimeType": "audio/mp4; codecs=\"mp4a.40.5\"",
          "bitrate": 50134,
          "initRange": {
            "start": "0",
            "end": "640"
          },
          "indexRange": {
            "start": "641",
            "end": "864"
          },
          "lastModified": "1634201977640971",
          "contentLength": "920541",
          "quality": "tiny",
          "projectionType": "RECTANGULAR",
          "averageBitrate": 48823,
          "audioQuality": "AUDIO_QUALITY_LOW",
          "approxDurationMs": "150836",
          "audioSampleRate": "22050",
          "audioChannels": 2
        },
        {
          "itag": 140,
          "url": "https://rr1---sn-jtcxg-aixr.googlevideo.com/videoplayback?expire=1721918184&ei=iA6iZsbDDrSbhcIP3vGAsAI&ip=72.255.32.221&id=o-AIfkNKKhLT-lA4V_ZUFTQvmtZdu6OuWKlqXK1t_z6xlr&itag=140&source=youtube&requiressl=yes&xpc=EgVo2aDSNQ%3D%3D&mh=Or&mm=31%2C29&mn=sn-jtcxg-aixr%2Csn-hju7enll&ms=au%2Crdu&mv=m&mvi=1&pl=24&initcwndbps=463750&vprv=1&svpuc=1&mime=audio%2Fmp4&rqh=1&gir=yes&clen=2440766&dur=150.767&lmt=1634201978352303&mt=1721896397&fvip=5&keepalive=yes&c=ANDROID_TESTSUITE&txp=5532434&sparams=expire%2Cei%2Cip%2Cid%2Citag%2Csource%2Crequiressl%2Cxpc%2Cvprv%2Csvpuc%2Cmime%2Crqh%2Cgir%2Cclen%2Cdur%2Clmt&sig=AJfQdSswRgIhAJW-DfjmDr3mI1v5GT6X2JSE1Fc0bC3hHGkr_iteMVdEAiEApp-iLjjEjc1_Q9_y8-wzgImDIFlCaWZhcDQMb_sA_nM%3D&lsparams=mh%2Cmm%2Cmn%2Cms%2Cmv%2Cmvi%2Cpl%2Cinitcwndbps&lsig=AGtxev0wRQIgKbqKmNZwRGPiI2UyTXhKIU8MGbso7laLX2z8k-XxzxQCIQCKQ2mzp1kpE79FK1iDmfx1J1vuKDLa0OzAkpZKisJhKw%3D%3D",
          "mimeType": "audio/mp4; codecs=\"mp4a.40.2\"",
          "bitrate": 130821,
          "initRange": {
            "start": "0",
            "end": "631"
          },
          "indexRange": {
            "start": "632",
            "end": "855"
          },
          "lastModified": "1634201978352303",
          "contentLength": "2440766",
          "quality": "tiny",
          "projectionType": "RECTANGULAR",
          "averageBitrate": 129511,
          "highReplication": true,
          "audioQuality": "AUDIO_QUALITY_MEDIUM",
          "approxDurationMs": "150767",
          "audioSampleRate": "44100",
          "audioChannels": 2
        },
        {
          "itag": 249,
          "url": "https://rr1---sn-jtcxg-aixr.googlevideo.com/videoplayback?expire=1721918184&ei=iA6iZsbDDrSbhcIP3vGAsAI&ip=72.255.32.221&id=o-AIfkNKKhLT-lA4V_ZUFTQvmtZdu6OuWKlqXK1t_z6xlr&itag=249&source=youtube&requiressl=yes&xpc=EgVo2aDSNQ%3D%3D&mh=Or&mm=31%2C29&mn=sn-jtcxg-aixr%2Csn-hju7enll&ms=au%2Crdu&mv=m&mvi=1&pl=24&initcwndbps=463750&vprv=1&svpuc=1&mime=audio%2Fwebm&rqh=1&gir=yes&clen=1038523&dur=150.721&lmt=1634201966694099&mt=1721896397&fvip=5&keepalive=yes&c=ANDROID_TESTSUITE&txp=5532434&sparams=expire%2Cei%2Cip%2Cid%2Citag%2Csource%2Crequiressl%2Cxpc%2Cvprv%2Csvpuc%2Cmime%2Crqh%2Cgir%2Cclen%2Cdur%2Clmt&sig=AJfQdSswRQIhAIJ4U8cqFCQMdrCAeb9eOX7Bq53jRltdg9eFiUnFfR3DAiBfHDk-WwN5QnKKfYxgpdmC5MLQTE_G4E4oKBFW48rliw%3D%3D&lsparams=mh%2Cmm%2Cmn%2Cms%2Cmv%2Cmvi%2Cpl%2Cinitcwndbps&lsig=AGtxev0wRQIgKbqKmNZwRGPiI2UyTXhKIU8MGbso7laLX2z8k-XxzxQCIQCKQ2mzp1kpE79FK1iDmfx1J1vuKDLa0OzAkpZKisJhKw%3D%3D",
          "mimeType": "audio/webm; codecs=\"opus\"",
          "bitrate": 62364,
          "initRange": {
            "start": "0",
            "end": "265"
          },
          "indexRange": {
            "start": "266",
            "end": "534"
          },
          "lastModified": "1634201966694099",
          "contentLength": "1038523",
          "quality": "tiny",
          "projectionType": "RECTANGULAR",
          "averageBitrate": 55122,
          "audioQuality": "AUDIO_QUALITY_LOW",
          "approxDurationMs": "150721",
          "audioSampleRate": "48000",
          "audioChannels": 2
        },
        {
          "itag": 250,
          "url": "https://rr1---sn-jtcxg-aixr.googlevideo.com/videoplayback?expire=1721918184&ei=iA6iZsbDDrSbhcIP3vGAsAI&ip=72.255.32.221&id=o-AIfkNKKhLT-lA4V_ZUFTQvmtZdu6OuWKlqXK1t_z6xlr&itag=250&source=youtube&requiressl=yes&xpc=EgVo2aDSNQ%3D%3D&mh=Or&mm=31%2C29&mn=sn-jtcxg-aixr%2Csn-hju7enll&ms=au%2Crdu&mv=m&mvi=1&pl=24&initcwndbps=463750&vprv=1&svpuc=1&mime=audio%2Fwebm&rqh=1&gir=yes&clen=1316173&dur=150.721&lmt=1634201978667703&mt=1721896397&fvip=5&keepalive=yes&c=ANDROID_TESTSUITE&txp=5532434&sparams=expire%2Cei%2Cip%2Cid%2Citag%2Csource%2Crequiressl%2Cxpc%2Cvprv%2Csvpuc%2Cmime%2Crqh%2Cgir%2Cclen%2Cdur%2Clmt&sig=AJfQdSswRgIhAOO7biCo8CDq_UTl0Q-6ZP5TLa9YIWg3xC-hn7PzM7Z7AiEAq0fvqcycBowZWe4IidOsz9etV2IOfmjLgyNiwRglaiM%3D&lsparams=mh%2Cmm%2Cmn%2Cms%2Cmv%2Cmvi%2Cpl%2Cinitcwndbps&lsig=AGtxev0wRQIgKbqKmNZwRGPiI2UyTXhKIU8MGbso7laLX2z8k-XxzxQCIQCKQ2mzp1kpE79FK1iDmfx1J1vuKDLa0OzAkpZKisJhKw%3D%3D",
          "mimeType": "audio/webm; codecs=\"opus\"",
          "bitrate": 76843,
          "initRange": {
            "start": "0",
            "end": "265"
          },
          "indexRange": {
            "start": "266",
            "end": "534"
          },
          "lastModified": "1634201978667703",
          "contentLength": "1316173",
          "quality": "tiny",
          "projectionType": "RECTANGULAR",
          "averageBitrate": 69860,
          "audioQuality": "AUDIO_QUALITY_LOW",
          "approxDurationMs": "150721",
          "audioSampleRate": "48000",
          "audioChannels": 2
        },
        {
          "itag": 251,
          "url": "https://rr1---sn-jtcxg-aixr.googlevideo.com/videoplayback?expire=1721918184&ei=iA6iZsbDDrSbhcIP3vGAsAI&ip=72.255.32.221&id=o-AIfkNKKhLT-lA4V_ZUFTQvmtZdu6OuWKlqXK1t_z6xlr&itag=251&source=youtube&requiressl=yes&xpc=EgVo2aDSNQ%3D%3D&mh=Or&mm=31%2C29&mn=sn-jtcxg-aixr%2Csn-hju7enll&ms=au%2Crdu&mv=m&mvi=1&pl=24&initcwndbps=463750&vprv=1&svpuc=1&mime=audio%2Fwebm&rqh=1&gir=yes&clen=2493794&dur=150.721&lmt=1634201983701862&mt=1721896397&fvip=5&keepalive=yes&c=ANDROID_TESTSUITE&txp=5532434&sparams=expire%2Cei%2Cip%2Cid%2Citag%2Csource%2Crequiressl%2Cxpc%2Cvprv%2Csvpuc%2Cmime%2Crqh%2Cgir%2Cclen%2Cdur%2Clmt&sig=AJfQdSswRQIhANb9KNXIzGOZJ-kgVm-TpdmUUjqmXhlmWkv82w7PgWtFAiAAlYDUd9QJOxTvAle7A0C7j4AKrimKvtwdHqXh2BRxFA%3D%3D&lsparams=mh%2Cmm%2Cmn%2Cms%2Cmv%2Cmvi%2Cpl%2Cinitcwndbps&lsig=AGtxev0wRQIgKbqKmNZwRGPiI2UyTXhKIU8MGbso7laLX2z8k-XxzxQCIQCKQ2mzp1kpE79FK1iDmfx1J1vuKDLa0OzAkpZKisJhKw%3D%3D",
          "mimeType": "audio/webm; codecs=\"opus\"",
          "bitrate": 146396,
          "initRange": {
            "start": "0",
            "end": "265"
          },
          "indexRange": {
            "start": "266",
            "end": "534"
          },
          "lastModified": "1634201983701862",
          "contentLength": "2493794",
          "quality": "tiny",
          "projectionType": "RECTANGULAR",
          "averageBitrate": 132366,
          "audioQuality": "AUDIO_QUALITY_MEDIUM",
          "approxDurationMs": "150721",
          "audioSampleRate": "48000",
          "audioChannels": 2
        }
      ]
    }
  }
}